{"mean":{"confidence_interval":{"confidence_level":0.95,"lower_bound":8516138.279958338,"upper_bound":8535929.652125003},"point_estimate":8525125.75166667,"standard_error":5102.448372306657},"median":{"confidence_interval":{"confidence_level":0.95,"lower_bound":8508283.5,"upper_bound":8517029.666666666},"point_estimate":8510484.25,"standard_error":2368.194434055623},"median_abs_dev":{"confidence_interval":{"confidence_level":0.95,"lower_bound":12817.323872446093,"upper_bound":22075.048758088655},"point_estimate":16854.072950780854,"standard_error":2126.8860254460833},"slope":null,"std_dev":{"confidence_interval":{"confidence_level":0.95,"lower_bound":27413.74244588347,"upper_bound":71402.54793704917},"point_estimate":51272.04861978105,"standard_error":11419.029454505308}}