{"mean":{"confidence_interval":{"confidence_level":0.95,"lower_bound":7446.150308988987,"upper_bound":7487.51410199472},"point_estimate":7463.090644084889,"standard_error":10.77140999580932},"median":{"confidence_interval":{"confidence_level":0.95,"lower_bound":7436.9874776386405,"upper_bound":7465.420928805237},"point_estimate":7453.173769110388,"standard_error":7.646448544890343},"median_abs_dev":{"confidence_interval":{"confidence_level":0.95,"lower_bound":36.99493094242073,"upper_bound":54.58043007894079},"point_estimate":48.54021623012147,"standard_error":4.480064453639181},"slope":{"confidence_interval":{"confidence_level":0.95,"lower_bound":7428.141108434468,"upper_bound":7447.7972382291855},"point_estimate":7437.440484932535,"standard_error":5.010436084145462},"std_dev":{"confidence_interval":{"confidence_level":0.95,"lower_bound":42.35616982610105,"upper_bound":174.15434297577596},"point_estimate":108.44624293591124,"standard_error":43.189509971321385}}