{"mean":{"confidence_interval":{"confidence_level":0.95,"lower_bound":6232964.86,"upper_bound":6255167.2293125},"point_estimate":6243911.92875,"standard_error":5633.713952736765},"median":{"confidence_interval":{"confidence_level":0.95,"lower_bound":6216111.875,"upper_bound":6249843.0},"point_estimate":6231966.4375,"standard_error":9208.306427764219},"median_abs_dev":{"confidence_interval":{"confidence_level":0.95,"lower_bound":37917.401664331555,"upper_bound":70863.6456169188},"point_estimate":52970.98049707711,"standard_error":8148.945102571723},"slope":null,"std_dev":{"confidence_interval":{"confidence_level":0.95,"lower_bound":49344.67923723622,"upper_bound":63130.16860462705},"point_estimate":56743.8812443014,"standard_error":3511.1103683522}}