{"mean":{"confidence_interval":{"confidence_level":0.95,"lower_bound":71613.50241137188,"upper_bound":74703.52503103945},"point_estimate":73059.0702929662,"standard_error":789.7337401209556},"median":{"confidence_interval":{"confidence_level":0.95,"lower_bound":71266.80319148937,"upper_bound":71619.82756132756},"point_estimate":71437.55692022263,"standard_error":96.4830297289417},"median_abs_dev":{"confidence_interval":{"confidence_level":0.95,"lower_bound":727.2676067312937,"upper_bound":2706.855572164896},"point_estimate":1032.53015671004,"standard_error":463.64272436307175},"slope":{"confidence_interval":{"confidence_level":0.95,"lower_bound":72325.47340114409,"upper_bound":73565.1553664041},"point_estimate":72906.94374802086,"standard_error":318.37644129770325},"std_dev":{"confidence_interval":{"confidence_level":0.95,"lower_bound":4394.135741490493,"upper_bound":10757.394451019814},"point_estimate":7920.26656430488,"standard_error":1619.9887367667268}}