{"mean":{"confidence_interval":{"confidence_level":0.95,"lower_bound":8626.28197755554,"upper_bound":8690.470619709977},"point_estimate":8659.364302880393,"standard_error":16.323738443100886},"median":{"confidence_interval":{"confidence_level":0.95,"lower_bound":8675.3314001657,"upper_bound":8710.173736570796},"point_estimate":8693.592793721262,"standard_error":8.092102056058307},"median_abs_dev":{"confidence_interval":{"confidence_level":0.95,"lower_bound":55.07877071333224,"upper_bound":94.18120870142435},"point_estimate":70.47673806834683,"standard_error":10.599179401464754},"slope":{"confidence_interval":{"confidence_level":0.95,"lower_bound":8686.3762651681,"upper_bound":8714.083716457148},"point_estimate":8699.474004294196,"standard_error":7.062302321243439},"std_dev":{"confidence_interval":{"confidence_level":0.95,"lower_bound":128.43826391013465,"upper_bound":193.85439572698672},"point_estimate":164.36298114566733,"standard_error":16.60509495460087}}