{"mean":{"confidence_interval":{"confidence_level":0.95,"lower_bound":6957.877041627339,"upper_bound":7016.711448231079},"point_estimate":6983.565109229117,"standard_error":15.217464902141641},"median":{"confidence_interval":{"confidence_level":0.95,"lower_bound":6943.7486559986555,"upper_bound":6978.304273504274},"point_estimate":6961.164474331639,"standard_error":8.40989473498989},"median_abs_dev":{"confidence_interval":{"confidence_level":0.95,"lower_bound":50.82749870491907,"upper_bound":82.11702904729275},"point_estimate":68.86073321803723,"standard_error":7.753540920673494},"slope":{"confidence_interval":{"confidence_level":0.95,"lower_bound":6961.041358767868,"upper_bound":6990.173852915148},"point_estimate":6975.608177467575,"standard_error":7.450036544427723},"std_dev":{"confidence_interval":{"confidence_level":0.95,"lower_bound":61.83496568616279,"upper_bound":228.71257362416316},"point_estimate":152.54998298627828,"standard_error":44.810434129019946}}