{"mean":{"confidence_interval":{"confidence_level":0.95,"lower_bound":46729095.527,"upper_bound":46789808.013124995},"point_estimate":46758603.555,"standard_error":15455.182516823706},"median":{"confidence_interval":{"confidence_level":0.95,"lower_bound":46696049.25,"upper_bound":46777110.5},"point_estimate":46736282.25,"standard_error":20229.423232249443},"median_abs_dev":{"confidence_interval":{"confidence_level":0.95,"lower_bound":97022.82487750053,"upper_bound":151593.62340867502},"point_estimate":122992.41666644812,"standard_error":13464.838815693822},"slope":null,"std_dev":{"confidence_interval":{"confidence_level":0.95,"lower_bound":120580.23993960962,"upper_bound":193246.66262268796},"point_estimate":155886.28045736675,"standard_error":18939.596373422835}}