{"mean":{"confidence_interval":{"confidence_level":0.95,"lower_bound":88367.85613156548,"upper_bound":90174.5489498584},"point_estimate":89089.72098342536,"standard_error":476.6942640944148},"median":{"confidence_interval":{"confidence_level":0.95,"lower_bound":88193.38717532466,"upper_bound":88316.43697008479},"point_estimate":88283.20899722015,"standard_error":33.343983860228406},"median_abs_dev":{"confidence_interval":{"confidence_level":0.95,"lower_bound":183.19829964612182,"upper_bound":306.2791416830886},"point_estimate":237.27228339950392,"standard_error":31.16510010151618},"slope":{"confidence_interval":{"confidence_level":0.95,"lower_bound":88335.53914245493,"upper_bound":88837.8872901659},"point_estimate":88550.23664675209,"standard_error":129.55985959112024},"std_dev":{"confidence_interval":{"confidence_level":0.95,"lower_bound":645.1533959260289,"upper_bound":7843.5408834989075},"point_estimate":4792.401552915399,"standard_error":2024.6861685828317}}