{"mean":{"confidence_interval":{"confidence_level":0.95,"lower_bound":79337.30737130828,"upper_bound":79607.8825067044},"point_estimate":79466.13851888003,"standard_error":69.0120991509256},"median":{"confidence_interval":{"confidence_level":0.95,"lower_bound":79341.59160685806,"upper_bound":79540.81741852147},"point_estimate":79399.78888888888,"standard_error":62.70451316386967},"median_abs_dev":{"confidence_interval":{"confidence_level":0.95,"lower_bound":333.6248171453476,"upper_bound":620.4181958507319},"point_estimate":440.1089013010968,"standard_error":74.20276690993325},"slope":{"confidence_interval":{"confidence_level":0.95,"lower_bound":79430.34959495814,"upper_bound":79680.97233754802},"point_estimate":79549.69251071376,"standard_error":63.82947801918381},"std_dev":{"confidence_interval":{"confidence_level":0.95,"lower_bound":493.74509233513965,"upper_bound":904.2410224948277},"point_estimate":689.1186893251115,"standard_error":108.5926679141059}}