{"mean":{"confidence_interval":{"confidence_level":0.95,"lower_bound":1060232.3700850988,"upper_bound":1065564.804478337},"point_estimate":1062532.878422709,"standard_error":1380.663982134545},"median":{"confidence_interval":{"confidence_level":0.95,"lower_bound":1058713.8723404256,"upper_bound":1060631.5043215211},"point_estimate":1059768.7678571427,"standard_error":582.496953898989},"median_abs_dev":{"confidence_interval":{"confidence_level":0.95,"lower_bound":2756.086374523933,"upper_bound":4585.561369000422},"point_estimate":3796.933909037093,"standard_error":484.7583272568881},"slope":{"confidence_interval":{"confidence_level":0.95,"lower_bound":1060622.496719282,"upper_bound":1066422.6303418174},"point_estimate":1062866.6955755875,"standard_error":1540.790434530758},"std_dev":{"confidence_interval":{"confidence_level":0.95,"lower_bound":4668.131433673385,"upper_bound":20752.464674944185},"point_estimate":13875.78914082648,"standard_error":4248.89730712886}}