{"mean":{"confidence_interval":{"confidence_level":0.95,"lower_bound":59559.60582870518,"upper_bound":60387.30087846933},"point_estimate":60031.937228120005,"standard_error":213.56856577631277},"median":{"confidence_interval":{"confidence_level":0.95,"lower_bound":60358.69447508936,"upper_bound":60636.08058631049},"point_estimate":60524.09715260017,"standard_error":69.54962462919624},"median_abs_dev":{"confidence_interval":{"confidence_level":0.95,"lower_bound":420.8080156467563,"upper_bound":707.7454299794653},"point_estimate":570.3634869595847,"standard_error":71.28072815035283},"slope":{"confidence_interval":{"confidence_level":0.95,"lower_bound":60718.405068003536,"upper_bound":60945.63943933784},"point_estimate":60823.82559688453,"standard_error":58.31062851246433},"std_dev":{"confidence_interval":{"confidence_level":0.95,"lower_bound":844.2344060784732,"upper_bound":3302.2358636798454},"point_estimate":2142.29255896004,"standard_error":675.8259947929506}}