{"mean":{"confidence_interval":{"confidence_level":0.95,"lower_bound":527333.6033870972,"upper_bound":527966.0829156127},"point_estimate":527638.9079395707,"standard_error":161.55936546159006},"median":{"confidence_interval":{"confidence_level":0.95,"lower_bound":527048.8210526316,"upper_bound":527737.6162790698},"point_estimate":527558.8525641025,"standard_error":149.2910729067999},"median_abs_dev":{"confidence_interval":{"confidence_level":0.95,"lower_bound":960.5771613697619,"upper_bound":1599.6860453399358},"point_estimate":1186.8880246101257,"standard_error":169.63358169664085},"slope":{"confidence_interval":{"confidence_level":0.95,"lower_bound":527457.8360409738,"upper_bound":528196.916602698},"point_estimate":527804.8619092655,"standard_error":189.2112853647431},"std_dev":{"confidence_interval":{"confidence_level":0.95,"lower_bound":1237.467647452099,"upper_bound":1992.1584527377297},"point_estimate":1624.0261230705623,"standard_error":193.64852640752224}}