{"mean":{"confidence_interval":{"confidence_level":0.95,"lower_bound":7777013.122464287,"upper_bound":7808663.541000001},"point_estimate":7789747.674285713,"standard_error":8276.55441138212},"median":{"confidence_interval":{"confidence_level":0.95,"lower_bound":7774085.142857143,"upper_bound":7776611.5},"point_estimate":7775406.0,"standard_error":718.7726900423137},"median_abs_dev":{"confidence_interval":{"confidence_level":0.95,"lower_bound":3538.7543371747493,"upper_bound":6993.529975839925},"point_estimate":4882.943013310432,"standard_error":915.9738871032731},"slope":null,"std_dev":{"confidence_interval":{"confidence_level":0.95,"lower_bound":10901.389413476296,"upper_bound":135562.29800684104},"point_estimate":83264.92153858229,"standard_error":34039.143914204906}}