{"mean":{"confidence_interval":{"confidence_level":0.95,"lower_bound":6533486.66709375,"upper_bound":6549738.782375},"point_estimate":6539258.67375,"standard_error":4883.3244092214045},"median":{"confidence_interval":{"confidence_level":0.95,"lower_bound":6532104.375,"upper_bound":6533563.875},"point_estimate":6532997.3125,"standard_error":403.86300003431353},"median_abs_dev":{"confidence_interval":{"confidence_level":0.95,"lower_bound":2244.7490226477385,"upper_bound":4055.0221230089624},"point_estimate":3124.672107025981,"standard_error":459.34383814753596},"slope":null,"std_dev":{"confidence_interval":{"confidence_level":0.95,"lower_bound":4841.210441014926,"upper_bound":83570.3941292014},"point_estimate":48981.465136838815,"standard_error":27900.138403913013}}