{"mean":{"confidence_interval":{"confidence_level":0.95,"lower_bound":51190136.1475,"upper_bound":51538075.381500006},"point_estimate":51371687.2,"standard_error":89070.36407634807},"median":{"confidence_interval":{"confidence_level":0.95,"lower_bound":51325467.0,"upper_bound":51542995.0},"point_estimate":51435478.0,"standard_error":54386.05223245525},"median_abs_dev":{"confidence_interval":{"confidence_level":0.95,"lower_bound":339550.2350717783,"upper_bound":765841.4642035961},"point_estimate":432013.32373023033,"standard_error":110572.32689375107},"slope":null,"std_dev":{"confidence_interval":{"confidence_level":0.95,"lower_bound":631202.4669519917,"upper_bound":1164499.410669859},"point_estimate":897353.8317754827,"standard_error":141014.34521232388}}