{"mean":{"confidence_interval":{"confidence_level":0.95,"lower_bound":6914025.012857142,"upper_bound":6971239.739464285},"point_estimate":6940754.3442857135,"standard_error":14712.051209775205},"median":{"confidence_interval":{"confidence_level":0.95,"lower_bound":6873856.285714285,"upper_bound":6879312.0},"point_estimate":6876267.642857144,"standard_error":1369.0307980508992},"median_abs_dev":{"confidence_interval":{"confidence_level":0.95,"lower_bound":6513.485284362816,"upper_bound":15876.315918139839},"point_estimate":9911.922124029586,"standard_error":2330.01966195153},"slope":null,"std_dev":{"confidence_interval":{"confidence_level":0.95,"lower_bound":97085.89952030014,"upper_bound":190909.43811286616},"point_estimate":147675.79754399165,"standard_error":24116.13409487358}}