{"mean":{"confidence_interval":{"confidence_level":0.95,"lower_bound":7776639.597142856,"upper_bound":7807450.207071431},"point_estimate":7788411.510000002,"standard_error":8237.6512148877},"median":{"confidence_interval":{"confidence_level":0.95,"lower_bound":7774144.0,"upper_bound":7776567.571428572},"point_estimate":7775053.142857143,"standard_error":623.5785676236625},"median_abs_dev":{"confidence_interval":{"confidence_level":0.95,"lower_bound":4966.49811182723,"upper_bound":7552.893765908838},"point_estimate":6452.38098544724,"standard_error":634.4452815123858},"slope":null,"std_dev":{"confidence_interval":{"confidence_level":0.95,"lower_bound":10898.482406997993,"upper_bound":137887.278393067},"point_estimate":82879.69841858979,"standard_error":38654.2726207009}}