{"mean":{"confidence_interval":{"confidence_level":0.95,"lower_bound":528921.1396651372,"upper_bound":530802.0498425561},"point_estimate":529710.5712648315,"standard_error":489.0872899942911},"median":{"confidence_interval":{"confidence_level":0.95,"lower_bound":528535.2108433734,"upper_bound":529213.3671328671},"point_estimate":528955.811359127,"standard_error":201.7675452697162},"median_abs_dev":{"confidence_interval":{"confidence_level":0.95,"lower_bound":1055.0251107566348,"upper_bound":1723.7514664829773},"point_estimate":1383.966765544635,"standard_error":174.5857015087205},"slope":{"confidence_interval":{"confidence_level":0.95,"lower_bound":528913.6786518159,"upper_bound":529589.0749087218},"point_estimate":529240.5945574109,"standard_error":172.25775465210896},"std_dev":{"confidence_interval":{"confidence_level":0.95,"lower_bound":1749.4943353278843,"upper_bound":7815.882679741279},"point_estimate":4933.487901058207,"standard_error":1795.3412014426162}}