{"mean":{"confidence_interval":{"confidence_level":0.95,"lower_bound":373353.57809680636,"upper_bound":374029.00283997285},"point_estimate":373652.2629159379,"standard_error":173.3801795116839},"median":{"confidence_interval":{"confidence_level":0.95,"lower_bound":373200.8992248062,"upper_bound":373586.3333333333},"point_estimate":373360.35590277775,"standard_error":92.15616666635685},"median_abs_dev":{"confidence_interval":{"confidence_level":0.95,"lower_bound":536.0453077672476,"upper_bound":940.300793661412},"point_estimate":750.6304333935216,"standard_error":104.18217764342782},"slope":{"confidence_interval":{"confidence_level":0.95,"lower_bound":373435.5218513757,"upper_bound":374105.4746760489},"point_estimate":373714.5849997537,"standard_error":172.75910754483866},"std_dev":{"confidence_interval":{"confidence_level":0.95,"lower_bound":779.972945815946,"upper_bound":2602.6220984939573},"point_estimate":1744.1379159608753,"standard_error":483.8929150708416}}