{"mean":{"confidence_interval":{"confidence_level":0.95,"lower_bound":79670.40799669,"upper_bound":80143.00421859713},"point_estimate":79888.95885597494,"standard_error":120.40445364345287},"median":{"confidence_interval":{"confidence_level":0.95,"lower_bound":79595.17726508304,"upper_bound":79913.625},"point_estimate":79755.5298611111,"standard_error":82.44021555858993},"median_abs_dev":{"confidence_interval":{"confidence_level":0.95,"lower_bound":412.16723491593285,"upper_bound":638.9583071006642},"point_estimate":537.5991009583707,"standard_error":58.90280624439924},"slope":{"confidence_interval":{"confidence_level":0.95,"lower_bound":79771.06473308845,"upper_bound":80183.91060260244},"point_estimate":79955.530590365,"standard_error":105.72048032563087},"std_dev":{"confidence_interval":{"confidence_level":0.95,"lower_bound":710.4860893226794,"upper_bound":1618.990128646712},"point_estimate":1211.9542841375662,"standard_error":231.7052380731154}}