{"mean":{"confidence_interval":{"confidence_level":0.95,"lower_bound":53371424.255,"upper_bound":53593570.82125},"point_estimate":53486712.71,"standard_error":56864.50067898465},"median":{"confidence_interval":{"confidence_level":0.95,"lower_bound":53516049.0,"upper_bound":53621129.0},"point_estimate":53553920.0,"standard_error":26789.70961728566},"median_abs_dev":{"confidence_interval":{"confidence_level":0.95,"lower_bound":179583.07233676332,"upper_bound":295802.416348457},"point_estimate":236691.155397892,"standard_error":28706.99304746711},"slope":null,"std_dev":{"confidence_interval":{"confidence_level":0.95,"lower_bound":400282.04512524104,"upper_bound":709584.5706873033},"point_estimate":568457.8670141248,"standard_error":78942.99479454968}}