{"mean":{"confidence_interval":{"confidence_level":0.95,"lower_bound":51127.553470913284,"upper_bound":51601.941190835925},"point_estimate":51302.70113761766,"standard_error":134.84440447975197},"median":{"confidence_interval":{"confidence_level":0.95,"lower_bound":51093.869,"upper_bound":51201.41638257576},"point_estimate":51139.64405095839,"standard_error":27.903286440157988},"median_abs_dev":{"confidence_interval":{"confidence_level":0.95,"lower_bound":181.70868214250444,"upper_bound":294.5415556049814},"point_estimate":243.8442303279065,"standard_error":28.341500074575},"slope":{"confidence_interval":{"confidence_level":0.95,"lower_bound":51102.65697060377,"upper_bound":51248.55076739504},"point_estimate":51167.57476769617,"standard_error":37.34964006789795},"std_dev":{"confidence_interval":{"confidence_level":0.95,"lower_bound":219.20997013102655,"upper_bound":2301.7752975439325},"point_estimate":1359.7052465873574,"standard_error":718.0604171426595}}