{"mean":{"confidence_interval":{"confidence_level":0.95,"lower_bound":6553776.795,"upper_bound":6573715.48125},"point_estimate":6563640.03125,"standard_error":5084.56661945506},"median":{"confidence_interval":{"confidence_level":0.95,"lower_bound":6545764.375,"upper_bound":6575865.5},"point_estimate":6560361.5625,"standard_error":7129.180422120803},"median_abs_dev":{"confidence_interval":{"confidence_level":0.95,"lower_bound":36716.95899814367,"upper_bound":61174.669463932514},"point_estimate":43793.22334751487,"standard_error":6263.550865561608},"slope":null,"std_dev":{"confidence_interval":{"confidence_level":0.95,"lower_bound":42530.11511735646,"upper_bound":58551.10399884521},"point_estimate":50841.98301838971,"standard_error":4089.3881390245047}}