{"mean":{"confidence_interval":{"confidence_level":0.95,"lower_bound":46841146.504125,"upper_bound":46922751.475},"point_estimate":46878035.14,"standard_error":20918.81827846708},"median":{"confidence_interval":{"confidence_level":0.95,"lower_bound":46817628.75,"upper_bound":46848213.5},"point_estimate":46827211.75,"standard_error":7360.151647605076},"median_abs_dev":{"confidence_interval":{"confidence_level":0.95,"lower_bound":47680.78580349684,"upper_bound":77299.61210265743},"point_estimate":60585.335974395275,"standard_error":7463.42852800728},"slope":null,"std_dev":{"confidence_interval":{"confidence_level":0.95,"lower_bound":93413.88283582388,"upper_bound":293832.6885286148},"point_estimate":210655.47988530342,"standard_error":49112.54905122088}}